{"type": "Feature", "id": 12510832, "geometry": {"type": "Point", "coordinates": [50.582199, 25.9275]}, "properties": {"woe:id": 12510832, "woe:parent_id": 1967061, "woe:name": "Shaikh Isa Airport", "woe:placetype": 14, "woe:placetype_name": "Airport", "woe:lang": "ENG", "iso:country": "BH", "meta:provider": ["geoplanet:7.3.1", "geoplanet:7.3.2", "geoplanet:7.4.0", "geoplanet:7.4.1", "geoplanet:7.5.1", "geoplanet:7.5.2", "geoplanet:7.6.0", "geoplanet:7.8.1", "geoplanet:7.9.0", "geoplanet:7.10.0", "geoplanet:8.0.0", "woeplanet:8.0.0"], "meta:indexed": "2020-08-20T20:26:11.074208", "meta:updated": "2020-10-14T12:10:36.504841", "woe:hierarchy": {"continent": 24865671, "country": 23424753, "town": 0, "planet": 1, "county": 0, "suburb": 0, "state": 56051602, "region": 0, "localadmin": 0}, "woe:timezone_id": 28350812, "woe:hash": "thegrpbydsm3", "woe:centroid": [50.582199, 25.9275], "geom:latitude": 25.9275, "geom:longitude": 50.582199, "geom:hash": "thegrpbydsm3", "woe:latitude": 25.9275, "geom:centroid": [50.582199, 25.9275], "woe:longitude": 50.582199, "woe:repo": "woeplanet-airport-bh", "geom:area": 0.0, "woe:scale": 19}}